pyaefis/__init__.py
pyaefis/pyaefis.py
pyaefis-0.0.1.11.dist-info/METADATA
pyaefis-0.0.1.11.dist-info/WHEEL
pyaefis-0.0.1.11.dist-info/top_level.txt
pyaefis-0.0.1.11.dist-info/RECORD
