Metadata-Version: 2.1
Name: pyaefis
Version: 0.0.1.11
Summary: Library for interacting with AEFIS
Home-page: https://github.com/cedarville-university/pyaefis
Author: Cedarville University
Author-email: techhelp@cedarville.edu
License: UNKNOWN
Platform: UNKNOWN
Classifier: Programming Language :: Python :: 3
Classifier: License :: OSI Approved :: MIT License
Classifier: Operating System :: OS Independent
Requires-Python: >=3.6
Requires-Dist: requests
Requires-Dist: urllib3
